Metadata-Version: 2.1
Name: alphadetector
Version: 0.0.26
Summary: object detection using yolo, tf2 and detectron2
Home-page: https://github.com/ravikanur/ObjectDetection_Webapp
Author: ravikanur
License: UNKNOWN
Project-URL: Bug Tracker, https://github.com/ravikanur/ObjectDetection_Webapp/issues
Platform: UNKNOWN
Requires-Python: >=3.7
License-File: LICENSE
Requires-Dist: absl-py (>=0.8.1)
Requires-Dist: astor (>=0.8.0)
Requires-Dist: Click (>=7.0)
Requires-Dist: gast (>=0.3.2)
Requires-Dist: google-pasta (>=0.1.7)
Requires-Dist: grpcio (>=1.24.1)
Requires-Dist: h5py (>=2.10.0)
Requires-Dist: requests
Requires-Dist: itsdangerous (>=1.1.0)
Requires-Dist: Jinja2 (>=2.10.3)
Requires-Dist: Keras-Applications (>=1.0.8)
Requires-Dist: Keras-Preprocessing (>=1.1.0)
Requires-Dist: Markdown (>=3.1.1)
Requires-Dist: MarkupSafe (>=1.1.1)
Requires-Dist: numpy (>=1.17.2)
Requires-Dist: opencv-python
Requires-Dist: Pillow (>=6.2.0)
Requires-Dist: protobuf (>=3.10.0)
Requires-Dist: six (>=1.12.0)
Requires-Dist: tensorboard (==2.5.0)
Requires-Dist: tensorflow (==2.5.0)
Requires-Dist: tensorflow-estimator (==2.5.0)
Requires-Dist: termcolor (==1.1.0)
Requires-Dist: Werkzeug (==0.16.0)
Requires-Dist: wincertstore (==0.2)
Requires-Dist: wrapt (>=1.11.2)
Requires-Dist: tf-slim
Requires-Dist: gdown
Requires-Dist: Cython
Requires-Dist: PyYAML (>=5.3)
Requires-Dist: tqdm (>=4.41.0)
Requires-Dist: scipy (>=1.4.1)
Requires-Dist: fvcore
Requires-Dist: cloudpickle
Requires-Dist: pandas
Requires-Dist: seaborn
Requires-Dist: torch (>=1.7.0torchvision>=0.8.1)
